LICENSE.txt
README.txt
setup.cfg
setup.py
docs/CONTRIBUTORS.txt
docs/HISTORY.txt
medialog/__init__.py
medialog.fullnamefield.egg-info/PKG-INFO
medialog.fullnamefield.egg-info/SOURCES.txt
medialog.fullnamefield.egg-info/dependency_links.txt
medialog.fullnamefield.egg-info/entry_points.txt
medialog.fullnamefield.egg-info/namespace_packages.txt
medialog.fullnamefield.egg-info/not-zip-safe
medialog.fullnamefield.egg-info/requires.txt
medialog.fullnamefield.egg-info/top_level.txt
medialog/fullnamefield/__init__.py
medialog/fullnamefield/config.py
medialog/fullnamefield/configure.zcml
medialog/fullnamefield/field.py
medialog/fullnamefield/interfaces.py
medialog/fullnamefield/content/__init__.py
medialog/fullnamefield/content/configure.zcml
medialog/fullnamefield/content/fullname.py
medialog/fullnamefield/profiles/default/metadata.xml
medialog/fullnamefield/profiles/test/factorytool.xml
medialog/fullnamefield/profiles/test/fullnamewidget_marker.txt
medialog/fullnamefield/profiles/test/types.xml
medialog/fullnamefield/profiles/test/types/Fullname.xml
medialog/fullnamefield/tests/__init__.py
medialog/fullnamefield/tests/base.py
medialog/fullnamefield/tests/test_fullnamefield.py